lightningpkg/__init__.py
lightningpkg/input.py
lightningpkg/list.py
lightningpkg/my.py
lightningpkg-0.0.1.dist-info/licenses/LICENSE
lightningpkg-0.0.1.dist-info/METADATA
lightningpkg-0.0.1.dist-info/WHEEL
lightningpkg-0.0.1.dist-info/top_level.txt
lightningpkg-0.0.1.dist-info/RECORD
